LICENSE
README.md
setup.py
citation_rabbot/__init__.py
citation_rabbot/__main__.py
citation_rabbot/arg.py
citation_rabbot/models.py
citation_rabbot/rabbot.py
citation_rabbot/start.py
citation_rabbot.egg-info/PKG-INFO
citation_rabbot.egg-info/SOURCES.txt
citation_rabbot.egg-info/dependency_links.txt
citation_rabbot.egg-info/requires.txt
citation_rabbot.egg-info/top_level.txt
citation_rabbot/jumps/__init__.py
citation_rabbot/jumps/detail.py
citation_rabbot/jumps/favorites.py
citation_rabbot/jumps/papers.py
citation_rabbot/jumps/papers_args.py
citation_rabbot/jumps/papers_display.py
citation_rabbot/jumps/papers_query.py
citation_rabbot/jumps/search.py